mesfix-1.0.0.dist-info/DESCRIPTION.rst
mesfix-1.0.0.dist-info/METADATA
mesfix-1.0.0.dist-info/RECORD
mesfix-1.0.0.dist-info/WHEEL
mesfix-1.0.0.dist-info/metadata.json
mesfix-1.0.0.dist-info/top_level.txt
mutils/__init__.py
mutils/helpers.py
mutils/httplib.py
mutils/mslog.py
mutils/queue.py
mutils/queue_msgs.py
mutils/queue_objs.py
mutils/queue_test.py
