Metadata-Version: 2.0
Name: mesfix
Version: 1.0.0
Summary: A library of all the common utilities used by the software artifacts at Mesfix
Home-page: https://github.com/adminMesfix/mutils
Author: Mesfix
Author-email: admin@mesfix.com
License: MIT
Keywords: utils logging AMPQ microservices
Platform: UNKNOWN
Classifier: Development Status :: 5 - Production/Stable
Classifier: Intended Audience :: Developers
Classifier: Topic :: Software Development :: Build Tools
Classifier: License :: OSI Approved :: MIT License
Classifier: Programming Language :: Python :: 2
Classifier: Programming Language :: Python :: 2.7
Classifier: Programming Language :: Python :: 3
Classifier: Programming Language :: Python :: 3.3
Classifier: Programming Language :: Python :: 3.4
Classifier: Programming Language :: Python :: 3.5
Requires-Dist: pika
Requires-Dist: requests
